<?xml version="1.0" ?><annotation>
	<folder>VOC2007</folder>
	<filename>001123.jpg</filename>
	<path>/home/wlw/下载/defect/JPEGImages/001123.jpg</path>
	<source>
		<database>Unknown</database>
	</source>
	<size>
		<width>800</width>
		<height>600</height>
		<depth>1</depth>
	</size>
	<segmented>0</segmented>
	<object>
		<name>defect</name>
		<pose>Unspecified</pose>
		<truncated>0</truncated>
		<difficult>0</difficult>
		<bndbox>
			<xmin>299</xmin>
			<ymin>82</ymin>
			<xmax>445</xmax>
			<ymax>192</ymax>
		</bndbox>
	</object>
	<object>
		<name>defect</name>
		<pose>Unspecified</pose>
		<truncated>0</truncated>
		<difficult>0</difficult>
		<bndbox>
			<xmin>632</xmin>
			<ymin>121</ymin>
			<xmax>654</xmax>
			<ymax>140</ymax>
		</bndbox>
	</object>
	<object>
		<name>defect</name>
		<pose>Unspecified</pose>
		<truncated>0</truncated>
		<difficult>0</difficult>
		<bndbox>
			<xmin>698</xmin>
			<ymin>120</ymin>
			<xmax>715</xmax>
			<ymax>135</ymax>
		</bndbox>
	</object>
	<object>
		<name>defect</name>
		<pose>Unspecified</pose>
		<truncated>0</truncated>
		<difficult>0</difficult>
		<bndbox>
			<xmin>730</xmin>
			<ymin>128</ymin>
			<xmax>761</xmax>
			<ymax>151</ymax>
		</bndbox>
	</object>
</annotation>